[{"id":1,"city":"Tangping","address":"Suite 89","status":"sold","created_at":"11/14/2024"},
{"id":2,"city":"Ankou","address":"Suite 98","status":"on_sale","created_at":"8/11/2024"},
{"id":3,"city":"Al Ghuwayrīyah","address":"1st Floor","status":"sold","created_at":"6/27/2024"},
{"id":4,"city":"Ya’erya","address":"PO Box 14878","status":"on_sale","created_at":"4/8/2024"},
{"id":5,"city":"Anding","address":"Room 1313","status":"on_sale","created_at":"12/23/2024"},
{"id":6,"city":"Mercaderes","address":"15th Floor","status":"sold","created_at":"1/12/2025"},
{"id":7,"city":"Troitsk","address":"Suite 33","status":"on_sale","created_at":"11/8/2024"},
{"id":8,"city":"Smiltene","address":"12th Floor","status":"sold","created_at":"2/12/2025"},
{"id":9,"city":"Mirovice","address":"PO Box 30615","status":"sold","created_at":"8/17/2024"},
{"id":10,"city":"Oesapa","address":"Suite 17","status":"sold","created_at":"4/28/2024"},
{"id":11,"city":"Xinpu","address":"PO Box 66614","status":"on_sale","created_at":"5/2/2024"},
{"id":12,"city":"Bugana","address":"Suite 77","status":"sold","created_at":"9/7/2024"},
{"id":13,"city":"Yantianhe","address":"Apt 1828","status":"sold","created_at":"1/15/2025"},
{"id":14,"city":"San Pedro Carchá","address":"Apt 1151","status":"sold","created_at":"3/5/2025"},
{"id":15,"city":"Castilla","address":"Apt 792","status":"on_sale","created_at":"9/7/2024"},
{"id":16,"city":"Huangnaihai","address":"5th Floor","status":"on_sale","created_at":"5/13/2024"},
{"id":17,"city":"Sudogda","address":"11th Floor","status":"on_sale","created_at":"9/24/2024"},
{"id":18,"city":"Évreux","address":"Apt 1949","status":"sold","created_at":"8/3/2024"},
{"id":19,"city":"Saint-Brieuc","address":"PO Box 65353","status":"sold","created_at":"2/14/2025"},
{"id":20,"city":"Dongmaku","address":"Room 53","status":"on_sale","created_at":"5/9/2024"},
{"id":21,"city":"Liangbing","address":"Apt 1332","status":"sold","created_at":"8/7/2024"},
{"id":22,"city":"Belyayevka","address":"PO Box 14951","status":"sold","created_at":"6/23/2024"},
{"id":23,"city":"Palangan","address":"Apt 1970","status":"sold","created_at":"1/29/2025"},
{"id":24,"city":"Obama","address":"Suite 33","status":"on_sale","created_at":"11/3/2024"},
{"id":25,"city":"Nabari","address":"Apt 1332","status":"on_sale","created_at":"7/23/2024"},
{"id":26,"city":"Sławoborze","address":"Room 517","status":"sold","created_at":"11/9/2024"},
{"id":27,"city":"Tromsø","address":"Room 1308","status":"on_sale","created_at":"5/16/2024"},
{"id":28,"city":"La Huaca","address":"Suite 64","status":"sold","created_at":"11/14/2024"},
{"id":29,"city":"Daigo","address":"18th Floor","status":"on_sale","created_at":"9/12/2024"},
{"id":30,"city":"Nelidovo","address":"14th Floor","status":"on_sale","created_at":"11/13/2024"},
{"id":31,"city":"Baimi","address":"Room 788","status":"sold","created_at":"1/28/2025"},
{"id":32,"city":"Sbikha","address":"Suite 1","status":"sold","created_at":"5/25/2024"},
{"id":33,"city":"Agara","address":"16th Floor","status":"on_sale","created_at":"1/31/2025"},
{"id":34,"city":"Longzhong","address":"Room 458","status":"on_sale","created_at":"5/3/2024"},
{"id":35,"city":"Bayanbulag","address":"Room 1107","status":"sold","created_at":"7/11/2024"},
{"id":36,"city":"Sukošan","address":"Apt 1882","status":"on_sale","created_at":"7/14/2024"},
{"id":37,"city":"Rive-de-Gier","address":"Suite 96","status":"sold","created_at":"6/1/2024"},
{"id":38,"city":"Canto","address":"PO Box 12330","status":"on_sale","created_at":"5/27/2024"},
{"id":39,"city":"Sant Cugat Del Valles","address":"Suite 11","status":"on_sale","created_at":"9/18/2024"},
{"id":40,"city":"Izumo","address":"PO Box 42334","status":"on_sale","created_at":"5/25/2024"},
{"id":41,"city":"Desnogorsk","address":"Room 1219","status":"on_sale","created_at":"5/8/2024"},
{"id":42,"city":"Ishige","address":"7th Floor","status":"on_sale","created_at":"9/15/2024"},
{"id":43,"city":"Soio","address":"PO Box 92631","status":"sold","created_at":"7/2/2024"},
{"id":44,"city":"Perho","address":"Suite 2","status":"sold","created_at":"6/3/2024"},
{"id":45,"city":"Eixo","address":"15th Floor","status":"on_sale","created_at":"9/27/2024"},
{"id":46,"city":"Diaoluoshan","address":"PO Box 18702","status":"sold","created_at":"11/10/2024"},
{"id":47,"city":"Songgui","address":"Apt 1231","status":"on_sale","created_at":"1/26/2025"},
{"id":48,"city":"Mosrentgen","address":"PO Box 88840","status":"sold","created_at":"10/22/2024"},
{"id":49,"city":"Plavsk","address":"PO Box 82781","status":"sold","created_at":"10/2/2024"},
{"id":50,"city":"Baška Voda","address":"Room 1038","status":"on_sale","created_at":"7/22/2024"},
{"id":51,"city":"Tarsouat","address":"Room 1685","status":"sold","created_at":"3/16/2025"},
{"id":52,"city":"Būlaevo","address":"Apt 1966","status":"sold","created_at":"9/9/2024"},
{"id":53,"city":"Saint-Priest","address":"PO Box 78002","status":"sold","created_at":"2/2/2025"},
{"id":54,"city":"Huaidian","address":"Suite 7","status":"sold","created_at":"5/18/2024"},
{"id":55,"city":"Chahe","address":"Apt 827","status":"sold","created_at":"12/30/2024"},
{"id":56,"city":"Tanjungbalai","address":"Apt 225","status":"on_sale","created_at":"1/19/2025"},
{"id":57,"city":"Nizhniy Novgorod","address":"PO Box 62303","status":"on_sale","created_at":"11/5/2024"},
{"id":58,"city":"Belyy Gorodok","address":"PO Box 37133","status":"sold","created_at":"4/9/2024"},
{"id":59,"city":"Denver","address":"PO Box 19685","status":"on_sale","created_at":"3/11/2025"},
{"id":60,"city":"Oyo","address":"Apt 143","status":"sold","created_at":"8/21/2024"},
{"id":61,"city":"Konispol","address":"Room 1546","status":"sold","created_at":"8/11/2024"},
{"id":62,"city":"El Puerto","address":"Room 1166","status":"on_sale","created_at":"12/9/2024"},
{"id":63,"city":"Opaka","address":"Suite 20","status":"on_sale","created_at":"7/21/2024"},
{"id":64,"city":"Santiago de Subrrifana","address":"Room 353","status":"sold","created_at":"1/12/2025"},
{"id":65,"city":"Darenzhuang","address":"Room 781","status":"sold","created_at":"9/2/2024"},
{"id":66,"city":"Ambulong","address":"Suite 90","status":"sold","created_at":"5/8/2024"},
{"id":67,"city":"Wangba","address":"19th Floor","status":"on_sale","created_at":"11/9/2024"},
{"id":68,"city":"Canggetelo","address":"PO Box 55590","status":"sold","created_at":"12/7/2024"},
{"id":69,"city":"Mouquim","address":"Apt 500","status":"on_sale","created_at":"12/12/2024"},
{"id":70,"city":"Meziměstí","address":"Apt 952","status":"sold","created_at":"4/8/2024"},
{"id":71,"city":"Kavieng","address":"8th Floor","status":"on_sale","created_at":"11/4/2024"},
{"id":72,"city":"Rio Grande da Serra","address":"Room 1123","status":"on_sale","created_at":"9/1/2024"},
{"id":73,"city":"Mucllo","address":"PO Box 9336","status":"sold","created_at":"3/31/2024"},
{"id":74,"city":"São Miguel de Machede","address":"16th Floor","status":"on_sale","created_at":"7/8/2024"},
{"id":75,"city":"Hangzhou","address":"Suite 65","status":"sold","created_at":"12/30/2024"},
{"id":76,"city":"Dawusu","address":"9th Floor","status":"on_sale","created_at":"5/5/2024"},
{"id":77,"city":"Amherst","address":"11th Floor","status":"sold","created_at":"11/6/2024"},
{"id":78,"city":"Dzięgielów","address":"PO Box 32789","status":"sold","created_at":"1/15/2025"},
{"id":79,"city":"Santa Catalina","address":"Room 1042","status":"sold","created_at":"2/21/2025"},
{"id":80,"city":"Otrokovice","address":"Apt 8","status":"on_sale","created_at":"3/27/2025"},
{"id":81,"city":"Wantou","address":"Suite 53","status":"sold","created_at":"4/4/2024"},
{"id":82,"city":"Liping","address":"Room 1104","status":"on_sale","created_at":"11/24/2024"},
{"id":83,"city":"Maglaj","address":"Apt 1023","status":"on_sale","created_at":"1/5/2025"},
{"id":84,"city":"Degeberga","address":"Room 1977","status":"on_sale","created_at":"6/27/2024"},
{"id":85,"city":"Byczyna","address":"Room 821","status":"sold","created_at":"1/5/2025"},
{"id":86,"city":"Khotsimsk","address":"13th Floor","status":"sold","created_at":"2/17/2025"},
{"id":87,"city":"Welisara","address":"Room 771","status":"sold","created_at":"4/17/2024"},
{"id":88,"city":"Baie-Comeau","address":"Suite 94","status":"on_sale","created_at":"6/9/2024"},
{"id":89,"city":"Lopandino","address":"Suite 4","status":"on_sale","created_at":"3/19/2025"},
{"id":90,"city":"Xianghuaqiao","address":"Apt 941","status":"sold","created_at":"3/11/2025"},
{"id":91,"city":"Shangma","address":"9th Floor","status":"sold","created_at":"3/5/2025"},
{"id":92,"city":"Fizuli","address":"PO Box 55590","status":"on_sale","created_at":"1/15/2025"},
{"id":93,"city":"Margherita","address":"PO Box 97437","status":"on_sale","created_at":"1/12/2025"},
{"id":94,"city":"Agarsin","address":"Suite 92","status":"on_sale","created_at":"12/31/2024"},
{"id":95,"city":"Ten’gushevo","address":"Apt 1178","status":"on_sale","created_at":"1/10/2025"},
{"id":96,"city":"Matang","address":"Room 878","status":"sold","created_at":"2/27/2025"},
{"id":97,"city":"São Bento do Sul","address":"Room 1514","status":"sold","created_at":"9/28/2024"},
{"id":98,"city":"Sukamaju","address":"PO Box 50876","status":"sold","created_at":"12/22/2024"},
{"id":99,"city":"Elías","address":"PO Box 59996","status":"sold","created_at":"12/28/2024"},
{"id":100,"city":"Mafang","address":"Apt 1828","status":"on_sale","created_at":"5/23/2024"}]